healthbox.py
pyhealthbox/__init__.py
pyhealthbox/healthbox.py
pyhealthbox-0.0.4.dist-info/LICENSE
pyhealthbox-0.0.4.dist-info/METADATA
pyhealthbox-0.0.4.dist-info/WHEEL
pyhealthbox-0.0.4.dist-info/top_level.txt
pyhealthbox-0.0.4.dist-info/RECORD
