Metadata-Version: 2.1
Name: pyhealthbox
Version: 0.0.4
Summary: Python Client to interact with the Renson Healthbox 3.0 Ventilation system
Home-page: https://github.com/sdiepend/pyhealthbox
Author: Stijn Diependaele
Author-email: sdiepend@gmail.com
License: MIT
Project-URL: Documentation, https://github.com/sdiepend/pyhealthbox/blob/master/README.md
Keywords: client api library renson healthbox ventilation
Platform: UNKNOWN
Classifier: Development Status :: 2 - Pre-Alpha
Classifier: Intended Audience :: Developers
Classifier: License :: OSI Approved :: MIT License
Classifier: Topic :: Home Automation
Classifier: Programming Language :: Python :: 3.5
Classifier: Programming Language :: Python :: 3.6
Requires-Python: >=3.5
Requires-Dist: requests
